[[{"__type__":"cc.SceneAsset","_name":"GraphicsTest","scene":{"__id__":1},"asyncLoadAssets":null},{"__type__":"cc.Scene","_name":"New Node","_children":[{"__id__":2}],"_anchorPoint":{"__type__":"cc.Vec2"},"_trs":{"__type__":"TypedArray","ctor":"Float64Array","array":[0,0,0,0,0,0,1,1,1,1]}},{"__type__":"cc.Node","_name":"Canvas","_parent":{"__id__":1},"_children":[{"__id__":3},{"__id__":4},{"__id__":8}],"_components":[{"__type__":"cc.Canvas","node":{"__id__":2}},{"__type__":"cc.Widget","node":{"__id__":2},"_alignFlags":45}],"_contentSize":{"__type__":"cc.Size","width":960,"height":640},"_trs":{"__type__":"TypedArray","ctor":"Float64Array","array":[480,320,0,0,0,0,1,1,1,1]},"_id":"a5esZu+45LA5mBpvttspPD"},{"__type__":"cc.Node","_name":"Main Camera","_parent":{"__id__":2},"_components":[{"__type__":"cc.Camera","node":{"__id__":3},"_clearFlags":7,"_depth":-1}],"_contentSize":{"__type__":"cc.Size","width":960,"height":640},"_trs":{"__type__":"TypedArray","ctor":"Float64Array","array":[0,0,202.81232424876825,0,0,0,1,1,1,1]}},{"__type__":"cc.Node","_name":"New Node","_parent":{"__id__":2},"_children":[{"__id__":5}],"_components":[{"__type__":"cc.Graphics","node":{"__id__":4},"_enabled":false,"_materials":[{"__uuid__":"a1U5RdJRFMFL57BdJC9H1X"}],"_strokeColor":{"__type__":"cc.Color","r":246,"g":124,"b":124}},{"__type__":"3948fKVE09Au5BySdcoPz7x","node":{"__id__":4},"tx1":{"__id__":6},"txLogo":{"__id__":10}}],"_trs":{"__type__":"TypedArray","ctor":"Float64Array","array":[0,0,0,0,0,0,1,1,1,1]}},{"__type__":"cc.Node","_name":"hl2","_parent":{"__id__":4},"_components":[{"__type__":"cc.Sprite","node":{"__id__":5},"_materials":[{"__uuid__":"ecpdLyjvZBwrvm+cedCcQy"}],"_spriteFrame":{"__uuid__":"33nlB9gFhDe6zhNtXXp3fc"},"_type":4,"_isTrimmedMode":false}],"_contentSize":{"__type__":"cc.Size","width":32,"height":32},"_anchorPoint":{"__type__":"cc.Vec2","y":1},"_trs":{"__type__":"TypedArray","ctor":"Float64Array","array":[0,0,0,0,0,0,1,1,1,1]}},{"__type__":"cc.Sprite","node":{"__id__":7},"_materials":[{"__uuid__":"ecpdLyjvZBwrvm+cedCcQy"}],"_spriteFrame":{"__uuid__":"33nlB9gFhDe6zhNtXXp3fc"}},{"__type__":"cc.Node","_name":"brush2","_parent":{"__id__":8},"_components":[{"__id__":6}],"_contentSize":{"__type__":"cc.Size","width":32,"height":32},"_trs":{"__type__":"TypedArray","ctor":"Float64Array","array":[21,0,0,0,0,0,1,1,1,1]}},{"__type__":"cc.Node","_name":"New Layout","_parent":{"__id__":2},"_children":[{"__id__":9},{"__id__":7}],"_components":[{"__type__":"cc.Layout","node":{"__id__":8},"_layoutSize":{"__type__":"cc.Size","width":74,"height":32},"_resize":1,"_N$layoutType":1,"_N$spacingX":10},{"__type__":"cc.Widget","node":{"__id__":8},"_alignFlags":9,"_left":19.216000000000008,"_top":12.108000000000004}],"_contentSize":{"__type__":"cc.Size","width":74,"height":32},"_trs":{"__type__":"TypedArray","ctor":"Float64Array","array":[-423.784,291.892,0,0,0,0,1,1,1,1]}},{"__type__":"cc.Node","_name":"h3","_parent":{"__id__":8},"_components":[{"__id__":10}],"_contentSize":{"__type__":"cc.Size","width":32,"height":32},"_trs":{"__type__":"TypedArray","ctor":"Float64Array","array":[-21,0,0,0,0,0,1,1,1,1]}},{"__type__":"cc.Sprite","node":{"__id__":9},"_materials":[{"__uuid__":"ecpdLyjvZBwrvm+cedCcQy"}],"_spriteFrame":{"__uuid__":"ad4R8WBppJW4qFqFx8kvbF"}}],{"__type__":"cc.SpriteFrame","content":{"name":"brush2","texture":"8aXoZKiWBELqGxEPkbUwac","rect":[0,0,32,32],"offset":[0,0],"originalSize":[32,32],"capInsets":[0,0,0,0]}},{"__type__":"cc.SpriteFrame","content":{"name":"h3","texture":"53b0963ktB/LUAwa8jaA3I","rect":[0,0,32,32],"offset":[0,0],"originalSize":[32,32],"capInsets":[0,0,0,0]}}]